pwk.py
pwk-0.2.0.dist-info/LICENSE
pwk-0.2.0.dist-info/METADATA
pwk-0.2.0.dist-info/WHEEL
pwk-0.2.0.dist-info/entry_points.txt
pwk-0.2.0.dist-info/top_level.txt
pwk-0.2.0.dist-info/RECORD
