Metadata-Version: 2.1
Name: pwk
Version: 0.2.0
Summary: A simple tool for manipulating tabular data using Python expressions
Home-page: https://github.com/saeub/pwk
License: UNKNOWN
Project-URL: Bug Tracker, https://github.com/saeub/pwk/issues
Platform: UNKNOWN
Classifier: Programming Language :: Python :: 3
Classifier: License :: OSI Approved :: MIT License
Classifier: Operating System :: OS Independent
License-File: LICENSE
